myweather_reporter-1.0.1.dist-info/top_level.txt
myweather_reporter-1.0.1.dist-info/METADATA
myweather_reporter-1.0.1.dist-info/DESCRIPTION.rst
myweather_reporter-1.0.1.dist-info/metadata.json
myweather_reporter-1.0.1.dist-info/WHEEL
myweather_reporter-1.0.1.dist-info/RECORD
myweather_reporter-1.0.1.dist-info/entry_points.txt
weather_reporter/utils.py
weather_reporter/cli.py
