Metadata-Version: 2.0
Name: myweather-reporter
Version: 1.0.1
Summary: A Python package to get weather reports for any location.
Home-page: UNKNOWN
Author: ANOOP SINGH RANA
Author-email: UNKNOWN
License: MIT
Platform: UNKNOWN
Classifier: License :: OSI Approved :: MIT License
Classifier: Programming Language :: Python :: 3
Classifier: Programming Language :: Python :: 3.7
Requires-Dist: requests
